tor_refresh.py
tor_refresh/__init__.py
tor_refresh/clean.py
tor_refresh/exceptions.py
tor_refresh/logger.py
tor_refresh/tor.py
tor_refresh/utils.py
tor_refresh-0.4.6.dist-info/LICENSE
tor_refresh-0.4.6.dist-info/METADATA
tor_refresh-0.4.6.dist-info/WHEEL
tor_refresh-0.4.6.dist-info/entry_points.txt
tor_refresh-0.4.6.dist-info/top_level.txt
tor_refresh-0.4.6.dist-info/RECORD
