Metadata-Version: 2.1
Name: tor-refresh
Version: 0.4.6
Summary: Refresh your TOR circuit
Home-page: https://github.com/Fraccs/tor-refresh
Author: Francesco Aliprandi
Author-email: aliprandifrancescopp@gmail.com
Requires-Python: >=3.10
License-File: LICENSE
Requires-Dist: colorama
Requires-Dist: readchar
Requires-Dist: requests
Requires-Dist: requests[socks]
Requires-Dist: rich
Requires-Dist: stem
Requires-Dist: python-string-utils
Requires-Dist: typer
